[{
	"inputFiles": [
        "bower_components/angular/angular.js",
        "bower_components/angular-messages/angular-messages.js",
        "bower_components/angular-route/angular-route.js",
        "bower_components/angular-sanitize/angular-sanitize.js",
        "bower_components/json-formatter/dist/json-formatter.js",
        "bower_components/dynamics.js/lib/dynamics.js",
        "bower_components/gmaps-marker-clusterer/src/markerclusterer.js"
    ],
	"outputFileName": "docs/js/vendors.js",
	"minify": {
		"enabled": true
	}
}, {
	"inputFiles": [
        "bower_components/angular-i18n/angular-locale_en.js"
    ],
	"outputFileName": "docs/js/locale/en.js",
	"minify": {
		"enabled": true
	}
}, {
	"inputFiles": [
        "artisan/artisan.module.js",

        "artisan/components/canvas/painter.service.js",
        "artisan/components/expandable/expandable.directive.js",
        "artisan/components/forms/control.directive.js",
        "artisan/components/forms/validate.directive.js",
        "artisan/components/interactions/tap.directive.js",
        "artisan/components/modals/modal.directive.js",
        "artisan/components/modals/modal.provider.js",
        "artisan/components/nav/nav.directives.js",
        "artisan/components/nav/nav.factory.js",
        "artisan/components/popuppable/popuppable.directive.js",
        "artisan/components/scrollable/scrollable.directive.js",
        "artisan/components/scrollable/scrollable.factory.js",
        "artisan/components/video/video.directive.js",

        "artisan/core/animate/animate.factory.js",
        "artisan/core/datetime/calendar.directive.js",
        "artisan/core/datetime/calendar.service.js",
        "artisan/core/datetime/datetime.service.js",
        "artisan/core/datetime/range.factory.js",
        "artisan/core/datetime/relative.filter.js",
        "artisan/core/dom/dom.service.js",
        "artisan/core/events/events.factory.js",
        "artisan/core/filters/filters.js",
        "artisan/core/geom/point.factory.js",
        "artisan/core/geom/rect.factory.js",
        "artisan/core/geom/vector.factory.js",
        "artisan/core/hash/hash.factory.js",
        "artisan/core/promise/promise.factory.js",
        "artisan/core/state/state.factory.js",
        "artisan/core/style/style.factory.js",
        "artisan/core/utils/utils.service.js",

        "artisan/environment/environment.provider.js",

        "artisan/models/doc.factory.js",
        "artisan/models/route.factory.js",
        "artisan/models/view.factory.js",

        "artisan/net/auth/auth.service.js",
        "artisan/net/bearer/bearer.service.js",
        "artisan/net/http/http.service.js",
        "artisan/net/preload/preload.factory.js",
        "artisan/net/once/once.service.js",
        "artisan/net/router/router.service.js",
        "artisan/net/silent/silent.service.js",
        "artisan/net/storage/storage.service.js",
        "artisan/net/trust/trust.service.js",

        "artisan/plugins/facebook/facebook.service.js",
        "artisan/plugins/google/google.service.js",
        "artisan/plugins/googlemaps/googlemaps.directive.js",
        "artisan/plugins/googlemaps/googlemaps.service.js",
        "artisan/plugins/mapbox/mapbox.directive.js",
        "artisan/plugins/mapbox/mapbox.service.js"

    ],
	"outputFileName": "docs/js/artisan.js",
	"minify": {
		"enabled": true
	}
}, {
	"inputFiles": [
        "app/app.module.js",
        "app/app.api.js",
        "app/app.routes.js",
        "app/app.run.js",

        "app/components/todo.directive.js",

        "app/controllers/contact-us.controller.js",
        "app/controllers/home.controller.js",
        "app/controllers/root.controller.js",
        "app/controllers/slug.controller.js",
        "app/controllers/test.controller.js",

        "app/environment/environment.js",
        "app/environment/environment.local.js",
        "app/environment/environment.production.js",
        "app/environment/environment.stage.js"
    ],
	"outputFileName": "docs/js/app.js",
	"minify": {
		"enabled": true
	}
}, {
	"inputFiles": [
        "bower_components/animate.css/animate.css",
        "bower_components/json-formatter/dist/json-formatter.css",
        "bower_components/dat.gui/build/dat.gui.css"
    ],
	"outputFileName": "docs/css/vendors.css",
	"minify": {
		"enabled": true
	}
}, {
	"inputFiles": [
        "docs/css/bootstrap.css"
    ],
	"outputFileName": "docs/css/bootstrap.css",
	"minify": {
		"enabled": true
	}
}, {
	"inputFiles": [
        "docs/css/artisan.css"
    ],
	"outputFileName": "docs/css/artisan.css",
	"minify": {
		"enabled": true
	}
}, {
	"inputFiles": [
        "docs/css/app.css"
    ],
	"outputFileName": "docs/css/app.css",
	"minify": {
		"enabled": true
	}
}]